HDL/src/fifo.v
`timescale 1ns/1ps

module fifo #(
    parameter ADDRESS_WIDTH = 10, // 1024 entries (1 ram blocks)
    parameter DATA_WIDTH = 4      // 4 bits wide
) (
    input  wire                   write_clk_i,
    input  wire                   write_en_i,
    input  wire [DATA_WIDTH-1:0]  data_in_i,

    input  wire                   read_clk_i,
    input  wire                   read_en_i,
    output reg  [DATA_WIDTH-1:0]  data_out_o,

    output wire                   fifo_full_o,
    output reg                    fifo_half_full_o,
    output wire                   fifo_empty_o
);

    // Memory array
    reg [DATA_WIDTH-1:0] memory [0:(1 << ADDRESS_WIDTH) - 1];

    // Address width + 1 sized pointers allow index 2^N addresses
    reg [ADDRESS_WIDTH:0] write_addr = 0;
    reg [ADDRESS_WIDTH:0] read_addr = 0;
    // wire [ADDRESS_WIDTH:0] read_addr_gc;

    reg write_addr_2nd_msb;
    wire fifo_half_full_edge;
    reg [3:0] pulseCounter;

    // grey code read pointer to cross clock domains
    // assign read_add_gc = read_addr ^ (read_addr >> 1)

    // Status flags
    assign fifo_empty_o = 1'b0;
    assign fifo_full_o  = 1'b0;

    // Fifo is half full when write address 2nd msb changes
    // 8 bit address           (7 bit wide memory)
    // address: 0x00 -> 0x3f   memory written to: 0x00->0x3f
    // address: 0x40 -> 0x7f   memory written to: 0x40->0x7f
    // address: 0x80 -> 0xBf   memory written to: 0x00->0x3f
    // address: 0xC0 -> 0xff   memory written to: 0x40->0x7f

    assign fifo_half_full_edge = (write_addr[ADDRESS_WIDTH - 1] != write_addr_2nd_msb);

    // Fifo half full pulse
    always @(negedge write_clk_i) begin
        if (pulseCounter != 0 || fifo_half_full_edge) begin
            pulseCounter <= pulseCounter + 1'b1;
            fifo_half_full_o <= 1'b1;
        end else begin
            pulseCounter <= 0;
            fifo_half_full_o <= 1'b0;
        end
    end

    // Write process: Triggered on falling edge of write_clk (phy clock)
    always @(negedge write_clk_i) begin
        if (write_en_i) begin
            memory[write_addr[ADDRESS_WIDTH-1:0]] <= data_in_i;
            write_addr <= write_addr + 1'b1;
            write_addr_2nd_msb <= write_addr[ADDRESS_WIDTH - 1];
        end else begin
            write_addr <= write_addr;
        end
    end

    // Read process: Triggered on falling edge of read_clk (qspi clock)
    always @(negedge read_clk_i) begin
        if (read_en_i) begin
            data_out_o <= memory[read_addr[ADDRESS_WIDTH-1:0]];
            read_addr <= read_addr + 1'b1;
        end else begin
            data_out_o <= 0;
            read_addr <= read_addr;
        end
    end

    // Memory initialization
    integer i;
    initial begin
        for (i = 0; i < 256; i++) begin
            memory[2 * i] = i/16;
            memory[2 * i + 1] = i;

            memory[512 + 2 * i] = i/16;
            memory[512 + 2 * i + 1] = i;

            memory[1024 + 2 * i] = (255 - i)/16;
            memory[1024 + 2 * i + 1] = (255 - i);

            memory[1536 + 2 * i] = (255 - i)/16;
            memory[1536 + 2 * i + 1] = (255 - i);
        end
    end

endmodule

HDL/src/ieee1394_dv_extract.v
`timescale 1ns/1ps

module ieee1394_dv_extract (
    input  wire       rst_i,

    input  wire       phy_clk_i,

    input  wire       status_state_i,
    input  wire       receive_state_i,

    input  wire [3:0] data_i,
    output reg  [3:0] data_o,

    input wire        data_strobe_i,
    output reg        data_strobe_o

);


    /*
        one video frame is divided into 10 (12?) DIF sequences


        DIF sequency consists of

        Header section:         1 DIF block
        Subcode section:        2 DIF blocks
        VAUX section:           3 DIF blocks
        Audio section:          9 DIF blocks
        Video section:          135 DIF blocks

        DIF block consists of

        ID                      3 bytes
        data                    77 bytes
    */


    /*
        Firewire isochronous packet

        32bit header + 32bit header CRC

        first 16 bits is the data length in bytes

        data aligned to 32 bits

        32bit data CRC

    */

    reg [4:0]  headerNybbleCounter = 5'h10;             // counter for 8 bytes (16 nybbles) of header and CRC
    reg [4:0]  firstEightByteIgnoreCounter = 5'h10;     // counter to ignore the first 8 bytes of data which are not part of the dv data
    reg [16:0] dataNybbleCounter = 0;                   // counter for remaining nybbles. 2 * data length from the first 16bits of the packet header


    reg status_state_reg;
    reg ignore = 1'b0;

    always @(negedge phy_clk_i or posedge rst_i) begin

        if (rst_i) begin
            headerNybbleCounter <= 5'h10;
            firstEightByteIgnoreCounter <= 5'h10;
            dataNybbleCounter <= 0;

        end else begin

            if (receive_state_i == 1'b0) begin // TODO: check that dataNybbleCounter is 0 here
                headerNybbleCounter <= 5'h10;
                firstEightByteIgnoreCounter <= 5'h10;
                dataNybbleCounter <= 0;
                ignore <= 1'b0;

            end else if (data_strobe_i == 1'b1) begin

                // Get data length
                if (headerNybbleCounter >= 13) begin
                    dataNybbleCounter <= {dataNybbleCounter[12:1], data_i, 1'b0};
                    headerNybbleCounter <= headerNybbleCounter - 1;
                end

                // skip rest of header
                else if (headerNybbleCounter != 0) begin
                    headerNybbleCounter <= headerNybbleCounter - 1;
                    // ignore <= (dataNybbleCounter == 17'h1fffe);                  // Ignore non isochronous packets. Better way ?
                    ignore <= (dataNybbleCounter != 17'h003d0);
                end

                // ignore first 8 bytes
                else if (firstEightByteIgnoreCounter != 0) begin
                    firstEightByteIgnoreCounter <= firstEightByteIgnoreCounter - 1;
                    dataNybbleCounter <= dataNybbleCounter - 1;
                end

                // forward packet data
                else if (dataNybbleCounter != 0) begin
                    dataNybbleCounter <= dataNybbleCounter - 1;
                end
            end
        end
    end


    always @(negedge phy_clk_i) begin
        status_state_reg <= status_state_i; // delay

        if (!ignore && ((headerNybbleCounter == 0 && firstEightByteIgnoreCounter == 0 && dataNybbleCounter != 0))) begin //|| status_state_reg))  begin
            data_o <= data_i;
            data_strobe_o <= data_strobe_i;
        end else begin
            data_o <= 4'h0;
            data_strobe_o <= 1'b0;
        end
    end


endmodule

HDL/src/ieee1394.v
`timescale 1ns/1ps

/*

    Detect start of packet (via speed code) and convert 2 bit wide data from phy into nybbles synced to data strobe for writing into fifo

*/

module ieee1394 (
    input  wire       rst_i,            // system reset

    input  wire       phy_clk_i,        // ieee1394 phy clock
    input  wire [1:0] phy_ctl_i,        // control signals from phy
    input  wire [1:0] phy_data_i,       // phy data

    output wire [3:0] data_o,           // output for writing to fifo
    output reg        data_strobe_o,    // strobe indicating when data_o is valid

    output wire       receive_state_o,
    output wire       status_state_o
);

    localparam CTL_IDLE = 2'b00;
    localparam CTL_STATUS = 2'b10;
    localparam CTL_RECEIVE = 2'b01;

    localparam SPEED_CODE_S100 = 2'b00;


    reg [3:0] data_shift;               // shift register for incoming data
    reg data_strobe_temp;               // temp signal to dellay strobe to align with data
    // reg data_strobe_delay;
    reg receiving_data = 1'b0;

    always @(negedge phy_clk_i or posedge rst_i) begin
        if (rst_i) begin
            data_shift  <= 4'h0;
            data_strobe_temp <= 1'b0;
            receiving_data <= 1'b0;

        end else begin
            if (phy_ctl_i == CTL_IDLE) begin
                data_shift  <= 4'h0;
                data_strobe_temp <= 1'b0;
                receiving_data <= 1'b0;

            end else if (/*(phy_ctl_i == CTL_STATUS) ||*/ (receiving_data))  begin
                data_shift <= {data_shift[1:0], phy_data_i[0], phy_data_i[1]};
                data_strobe_temp <= ~data_strobe_temp;
                receiving_data <= 1'b1;

            end else if ((phy_ctl_i == CTL_RECEIVE) && (phy_data_i == SPEED_CODE_S100)) begin
                receiving_data <= 1'b1;

            end else begin
                data_shift  <= 4'h0;
                data_strobe_temp <= 1'b0;
                receiving_data <= 1'b0;
            end

        end
    end

    // always @(negedge phy_clk_i) begin
    //     data_strobe_delay <= data_strobe_temp;
    // end
    //
    // always @(negedge phy_clk_i) begin
    //     data_strobe_o <= data_strobe_delay;
    //     receive_state_o <= receiving_data;
    //     if (data_strobe_delay == 1'b1) begin
    //         data_o <= data_shift;
    //     end else begin
    //         data_o <= 4'h0;
    //     end
    // end

    always @(negedge phy_clk_i) begin
        data_strobe_o <= data_strobe_temp;
    end

    assign data_o = (data_strobe_o == 1'b1) ? data_shift : 4'h0;//4'bzzzz;
    assign receive_state_o = receiving_data;
    assign status_state_o = (phy_ctl_i == CTL_STATUS);

endmodule

HDL/src/qspi.v
`timescale 1ns/1ps

module qspi (
    // input  wire       rst,            // System reset
    input  wire       qspi_sclk_i,    // QSPI clock
    input  wire       qspi_cs_i,      // Chip select
    inout  wire [3:0] qspi_data_io,   // QSPI data bus (tri-state)
    output wire       data_fetch_o,   // High when ready for data
    input  wire [3:0] data_in_i       // Data to be transmitted
);

    // State definitions using localparam
    localparam IDLE          = 2'd0;
    localparam TRANSMIT_DATA = 2'd1;

    // Internal signals
    reg [1:0] qspi_state = IDLE;

    // Combinational Logic
    // data_fetch_o is '0' when IDLE, else '1'
    assign data_fetch_o = (qspi_state == IDLE) ? 1'b0 : 1'b1;

    // Tri-state logic for qspi_data_io
    // Driven by data_in_i during TRANSMIT_DATA state, otherwise High-Z
    assign qspi_data_io = (qspi_state == TRANSMIT_DATA) ? data_in_i : 4'bzzzz;

    // State Machine logic
    // Data is sampled on rising edge, propagated on falling edge.
    always @(negedge qspi_sclk_i or posedge qspi_cs_i) begin
        if (qspi_cs_i == 1'b1) begin
            qspi_state <= IDLE;
        end else begin
            case (qspi_state)
                IDLE: begin
                    if (qspi_cs_i == 1'b0) begin        // Chip select goes low to signal start
                        qspi_state <= TRANSMIT_DATA;
                    end else begin
                        qspi_state <= IDLE;
                    end
                end

                // TURNAROUND: begin
                //     // Move to transmit state after turnaround cycle
                //     qspi_state <= TRANSMIT_DATA;
                // end

                TRANSMIT_DATA: begin
                    if (qspi_cs_i == 1'b1) begin        // Keep transmitting as long as Chip select stays low
                        qspi_state <= IDLE;
                    end else begin
                        qspi_state <= TRANSMIT_DATA;
                    end
                end

                default: begin
                    qspi_state <= IDLE;
                end
            endcase
        end
    end

    // localparam DATA_WIDTH    = 4;
    // localparam ADDRESS_WIDTH = 5;
    //
    // reg [(DATA_WIDTH-1):0] data_in_i_tmp;
    // reg [(ADDRESS_WIDTH-1):0] counter = 5'h0;
    //
    // always @(negedge qspi_sclk_i) begin
    //     counter = counter + 1;
    //     data_in_i_tmp = memory[counter];
    // end
    //
    // reg [DATA_WIDTH-1:0] memory [0:(1 << ADDRESS_WIDTH) - 1];
    // initial begin
    //     memory[0] = 4'h4;
    //     memory[1] = 4'h8;
    //     memory[2] = 4'h6;
    //     memory[3] = 4'h5;
    //     memory[4] = 4'h6;
    //     memory[5] = 4'hC;
    //     memory[6] = 4'h6;
    //     memory[7] = 4'hC;
    //     memory[8] = 4'h6;
    //     memory[9] = 4'hF;
    //
    //     memory[10] = 4'h2;
    //     memory[11] = 4'h0;
    //
    //     memory[12] = 4'h5;
    //     memory[13] = 4'h7;
    //     memory[14] = 4'h6;
    //     memory[15] = 4'hF;
    //     memory[16] = 4'h7;
    //     memory[17] = 4'h2;
    //     memory[18] = 4'h6;
    //     memory[19] = 4'hC;
    //     memory[20] = 4'h6;
    //     memory[21] = 4'h4;
    //     memory[22] = 4'h2;
    //     memory[23] = 4'h1;
    //
    //     memory[24] = 4'h3;
    //     memory[25] = 4'h1;
    //     memory[26] = 4'h3;
    //     memory[27] = 4'h2;
    //     memory[28] = 4'h3;
    //     memory[29] = 4'h3;
    //     memory[30] = 4'h2;
    //     memory[31] = 4'h0;
    // end

endmodule

HDL/src/blinky.v

`timescale 1ns/1ps
module blinky (
    input wire clk,
    output led1,
    output led2,
    output led3
);

    localparam BITS = 3;
    localparam LOG2DELAY = 25;

    reg [BITS+LOG2DELAY-1:0] counter = 0;
    reg [BITS-1:0] outcnt;

    always @(posedge clk) begin
        counter <= counter + 1;
        outcnt <= counter >> LOG2DELAY;
    end

    assign {led1, led2, led3} = outcnt ^ (outcnt >> 1);
endmodule

HDL/src/top.v
`timescale 1ns/1ps

module top (
    input  wire       quad_spi_clk,         // QSPI clock
    input  wire       quad_spi_cs,          // QSPI chip select
    inout  wire [3:0] quad_spi_data,        // QSPI data bus (tri-state)

    input  wire       phy_clk,              // Clock from IEE1394 PHY
    output wire       phy_rst,              // Active low PHY reset signal
    output  wire      phy_lreq,             // PHY link request
    input  wire [1:0] phy_ctl,              //
    input  wire [7:0] phy_data,             // PHY data bus         -- Should be inout?

    output wire       fifo_full,
    output wire       fifo_half_full,
    output wire       fifo_empty,

    output wire [2:0] led,

    input wire        error_status
);

    //reg clk_48;

    assign phy_rst = 1'bz;

    // 48MHz internal oscilllator

    wire qspi_data_ready;
    wire [3:0] qspi_tx_data;


    assign phy_lreq = 1'b0;


    blinky b(
    .clk(phy_clk),
    .led1(led[0]),
    .led2(led[1]),
    .led3(led[2])
);

    qspi quad_spi (
        // .rst(1'b0),
        .qspi_sclk_i(quad_spi_clk),
        .qspi_cs_i(quad_spi_cs),
        .qspi_data_io(quad_spi_data),
        .data_fetch_o(qspi_data_ready),
        .data_in_i(qspi_tx_data)
    );

//     llcreq lreq (
//         .phy_clk_i(phy_clk),
//         .rst(error_status),
//         .lreq_o(phy_lreq)
// );

    wire phy_data_available;
    wire dv_data_available;
    wire [3:0] phy_rx_data;
    wire [3:0] dv_rx_data;
    wire phy_receiving;

    wire phy_status;


    ieee1394 firewire (
        // .clk_i(clk_48),
        .rst_i(1'b0),

        .phy_clk_i(phy_clk),
        .phy_ctl_i(phy_ctl),
        .phy_data_i(phy_data[1:0]),

        .data_o(phy_rx_data),
        .data_strobe_o(phy_data_available),

        .receive_state_o(phy_receiving),
        .status_state_o(phy_status)
    );


    ieee1394_dv_extract dv (
        .rst_i(1'b0),

        .phy_clk_i(phy_clk),

        .receive_state_i(phy_receiving),
        .status_state_i(phy_status),

        .data_i(phy_rx_data),
        .data_o(dv_rx_data),

        .data_strobe_i(phy_data_available),
        .data_strobe_o(dv_data_available)

    );

    // 32 Kbit fifo
    fifo  #(
        .ADDRESS_WIDTH(11)
    )
    fifo
    (
        .write_clk_i(phy_clk),
        .write_en_i(dv_data_available),
        // .write_en_i(phy_data_available),
        .data_in_i(dv_rx_data),
        // .data_in_i(phy_rx_data),

        .read_clk_i(quad_spi_clk),
        .read_en_i(qspi_data_ready),
        .data_out_o(qspi_tx_data),

        // .fifo_empty_o(fifo_empty),
        .fifo_half_full_o(fifo_half_full),
        .fifo_full_o(fifo_full)
    );


endmodule

HDL/testbench/tb.v
`timescale 1ns/1ps

module tb ();

    reg clk;
    reg cs;
    reg phy_clk_t;
    reg [1:0] ctl_t;
    reg [1:0] phy_data_t;
    reg empty_t;
    reg hf_t;
    reg [5:0] phy_data_pad_t;

    reg first_read_t;

    integer i;

    // qspi read out when fifo half full
    initial begin

        clk = 1'b0;
        cs = 1'b0;
        first_read_t = 1'b1;

        // forever begin
        //
        //     if (hf_t == 1'b1) begin
        //
        //         #10 cs = 1'b0;
        //
        //         if (first_read_t) begin
        //             first_read_t = 1'b0;
        //             #10 clk = ~clk;
        //             #10 clk = ~clk;
        //         end
        //
        //         for(i = 0; i < 1024; i = i + 1) begin
        //             #10 clk = ~clk;
        //         end
        //
        //         #100 cs = 1'b0;
        //
        //     end else begin
        //         #20;
        //     end
        // end

        forever begin
            #10 clk = ~clk;
        end


    end


    // phy clock 50 Mhz
    initial begin

        phy_clk_t = 1'b0;

        forever begin
            #10 phy_clk_t = ~phy_clk_t;
        end
    end


    initial begin

        ctl_t = 2'b00;

        #10; // align changes to phy_clk rising edge

        forever begin

            // non iso packet

            #20 ctl_t = 2'b01; phy_data_t = 2'b11;
            #80 phy_data_t = 2'b00; // Speed code

            // 0xffff for 'length'
            #20 phy_data_t = 2'b11;
            #20 phy_data_t = 2'b11;
            #20 phy_data_t = 2'b11;
            #20 phy_data_t = 2'b11;
            #20 phy_data_t = 2'b11;
            #20 phy_data_t = 2'b11;
            #20 phy_data_t = 2'b11;
            #20 phy_data_t = 2'b11;

            // don't care data for rest of header
            #480

            // 4 bytes of data
            #320 phy_data_t = 2'b10;

            // don't care for data CRC
            #320 ctl_t = 2'b00;

            // iso packet

            #200 ctl_t = 2'b01; phy_data_t = 2'b11;

            #80 phy_data_t = 2'b00; // Speed code

            // length = 12
            #20 phy_data_t = 2'b00;
            #20 phy_data_t = 2'b00;
            #20 phy_data_t = 2'b00;
            #20 phy_data_t = 2'b00;

            #20 phy_data_t = 2'b00;
            #20 phy_data_t = 2'b00;
            #20 phy_data_t = 2'b11;
            #20 phy_data_t = 2'b00;

            // don't care data for rest of header
            #480

            // data = 1,2,3,4 ...
            #20 phy_data_t = 2'b00;
            #20 phy_data_t = 2'b00;
            #20 phy_data_t = 2'b00;
            #20 phy_data_t = 2'b10;

            #20 phy_data_t = 2'b00;
            #20 phy_data_t = 2'b00;
            #20 phy_data_t = 2'b00;
            #20 phy_data_t = 2'b01;

            #20 phy_data_t = 2'b00;
            #20 phy_data_t = 2'b00;
            #20 phy_data_t = 2'b00;
            #20 phy_data_t = 2'b11;

            #20 phy_data_t = 2'b00;
            #20 phy_data_t = 2'b00;
            #20 phy_data_t = 2'b10;
            #20 phy_data_t = 2'b00;

            #20 phy_data_t = 2'b00;
            #20 phy_data_t = 2'b00;
            #20 phy_data_t = 2'b10;
            #20 phy_data_t = 2'b10;

            #20 phy_data_t = 2'b00;
            #20 phy_data_t = 2'b00;
            #20 phy_data_t = 2'b10;
            #20 phy_data_t = 2'b01;

            #20 phy_data_t = 2'b00;
            #20 phy_data_t = 2'b00;
            #20 phy_data_t = 2'b10;
            #20 phy_data_t = 2'b11;

            #20 phy_data_t = 2'b00;
            #20 phy_data_t = 2'b00;
            #20 phy_data_t = 2'b01;
            #20 phy_data_t = 2'b00;


            // 9 - 12
            #20 phy_data_t = 2'b00;
            #20 phy_data_t = 2'b00;
            #20 phy_data_t = 2'b01;
            #20 phy_data_t = 2'b10;

            #20 phy_data_t = 2'b00;
            #20 phy_data_t = 2'b00;
            #20 phy_data_t = 2'b01;
            #20 phy_data_t = 2'b01;

            #20 phy_data_t = 2'b00;
            #20 phy_data_t = 2'b00;
            #20 phy_data_t = 2'b01;
            #20 phy_data_t = 2'b11;

            #20 phy_data_t = 2'b00;
            #20 phy_data_t = 2'b00;
            #20 phy_data_t = 2'b11;
            #20 phy_data_t = 2'b00;

            // don't care for data CRC
            #320 ctl_t = 2'b00;



            // iso packet
            /*
            #200 ctl_t = 2'b01; phy_data_t = 2'b11;

            #80 phy_data_t = 2'b00; // Speed code

            // length = 512
            #20 phy_data_t = 2'b00;
            #20 phy_data_t = 2'b00;
            #20 phy_data_t = 2'b00;
            #20 phy_data_t = 2'b10;

            #20 phy_data_t = 2'b00;
            #20 phy_data_t = 2'b00;
            #20 phy_data_t = 2'b00;
            #20 phy_data_t = 2'b00;

            // don't care data for rest of header
            #480

            // data = 0,1,2,3
            #20 phy_data_t = 2'b00;
            #20 phy_data_t = 2'b00;
            #20 phy_data_t = 2'b00;
            #20 phy_data_t = 2'b10;

            #20 phy_data_t = 2'b00;
            #20 phy_data_t = 2'b00;
            #20 phy_data_t = 2'b00;
            #20 phy_data_t = 2'b01;

            #20 phy_data_t = 2'b00;
            #20 phy_data_t = 2'b00;
            #20 phy_data_t = 2'b00;
            #20 phy_data_t = 2'b11;

            #20 phy_data_t = 2'b00;
            #20 phy_data_t = 2'b00;
            #20 phy_data_t = 2'b10;
            #20 phy_data_t = 2'b00;

            // more data
            #20000;

            // don't care for data CRC
            #320 ctl_t = 2'b00;
            */

            #500;
        end
    end


    // verilator lint_off PINMISSING
    top uut (
        .quad_spi_clk(clk),
        .quad_spi_cs(cs),

        .phy_clk(phy_clk_t),
        .phy_ctl(ctl_t),
        .phy_data({phy_data_pad_t, phy_data_t}),

        .fifo_empty(empty_t),
        .fifo_half_full(hf_t),

        .error_status(1'b1)
    );
    // verilator lint_on PINMISSING

    initial begin
        $dumpfile("tb.vcd");
        $dumpvars();
        #100000 $finish;
    end




endmodule

HDL/tb.vcd
$version Generated by VerilatedVcd $end
$timescale 1ps $end
 $scope module tb $end
  $var wire 1 5 clk $end
  $var wire 1 6 cs $end
  $var wire 1 7 phy_clk_t $end
  $var wire 2 8 ctl_t [1:0] $end
  $var wire 2 9 phy_data_t [1:0] $end
  $var wire 1 G empty_t $end
  $var wire 1 ( hf_t $end
  $var wire 6 H phy_data_pad_t [5:0] $end
  $var wire 1 : first_read_t $end
  $var wire 32 I i [31:0] $end
  $scope module uut $end
   $var wire 1 5 quad_spi_clk $end
   $var wire 1 6 quad_spi_cs $end
   $var wire 4 ; quad_spi_data [3:0] $end
   $var wire 1 7 phy_clk $end
   $var wire 1 J phy_rst $end
   $var wire 1 J phy_lreq $end
   $var wire 2 8 phy_ctl [1:0] $end
   $var wire 8 < phy_data [7:0] $end
   $var wire 1 J fifo_full $end
   $var wire 1 ( fifo_half_full $end
   $var wire 1 G fifo_empty $end
   $var wire 3 " led [2:0] $end
   $var wire 1 K error_status $end
   $var wire 1 = qspi_data_ready $end
   $var wire 4 > qspi_tx_data [3:0] $end
   $var wire 1 ? phy_data_available $end
   $var wire 1 ) dv_data_available $end
   $var wire 4 @ phy_rx_data [3:0] $end
   $var wire 4 * dv_rx_data [3:0] $end
   $var wire 1 0 phy_receiving $end
   $var wire 1 A phy_status $end
   $scope module b $end
    $var wire 1 7 clk $end
    $var wire 1 # led1 $end
    $var wire 1 $ led2 $end
    $var wire 1 % led3 $end
    $var wire 32 L BITS [31:0] $end
    $var wire 32 M LOG2DELAY [31:0] $end
    $var wire 28 & counter [27:0] $end
    $var wire 3 ' outcnt [2:0] $end
   $upscope $end
   $scope module dv $end
    $var wire 1 J rst_i $end
    $var wire 1 7 phy_clk_i $end
    $var wire 1 A status_state_i $end
    $var wire 1 0 receive_state_i $end
    $var wire 4 @ data_i [3:0] $end
    $var wire 4 * data_o [3:0] $end
    $var wire 1 ? data_strobe_i $end
    $var wire 1 ) data_strobe_o $end
    $var wire 5 1 headerNybbleCounter [4:0] $end
    $var wire 5 2 firstEightByteIgnoreCounter [4:0] $end
    $var wire 17 3 dataNybbleCounter [16:0] $end
    $var wire 1 + status_state_reg $end
    $var wire 1 4 ignore $end
   $upscope $end
   $scope module fifo $end
    $var wire 32 N ADDRESS_WIDTH [31:0] $end
    $var wire 32 O DATA_WIDTH [31:0] $end
    $var wire 1 7 write_clk_i $end
    $var wire 1 ) write_en_i $end
    $var wire 4 * data_in_i [3:0] $end
    $var wire 1 5 read_clk_i $end
    $var wire 1 = read_en_i $end
    $var wire 4 > data_out_o [3:0] $end
    $var wire 1 J fifo_full_o $end
    $var wire 1 ( fifo_half_full_o $end
    $var wire 1 J fifo_empty_o $end
    $var wire 12 , write_addr [11:0] $end
    $var wire 12 B read_addr [11:0] $end
    $var wire 1 - write_addr_2nd_msb $end
    $var wire 1 . fifo_half_full_edge $end
    $var wire 4 / pulseCounter [3:0] $end
    $var wire 32 C i [31:0] $end
   $upscope $end
   $scope module firewire $end
    $var wire 1 J rst_i $end
    $var wire 1 7 phy_clk_i $end
    $var wire 2 8 phy_ctl_i [1:0] $end
    $var wire 2 9 phy_data_i [1:0] $end
    $var wire 4 @ data_o [3:0] $end
    $var wire 1 ? data_strobe_o $end
    $var wire 1 0 receive_state_o $end
    $var wire 1 A status_state_o $end
    $var wire 2 P CTL_IDLE [1:0] $end
    $var wire 2 Q CTL_STATUS [1:0] $end
    $var wire 2 R CTL_RECEIVE [1:0] $end
    $var wire 2 P SPEED_CODE_S100 [1:0] $end
    $var wire 4 D data_shift [3:0] $end
    $var wire 1 E data_strobe_temp $end
    $var wire 1 0 receiving_data $end
   $upscope $end
   $scope module quad_spi $end
    $var wire 1 5 qspi_sclk_i $end
    $var wire 1 6 qspi_cs_i $end
    $var wire 4 ; qspi_data_io [3:0] $end
    $var wire 1 = data_fetch_o $end
    $var wire 4 > data_in_i [3:0] $end
    $var wire 2 P IDLE [1:0] $end
    $var wire 2 R TRANSMIT_DATA [1:0] $end
    $var wire 2 F qspi_state [1:0] $end
   $upscope $end
  $upscope $end
 $upscope $end
$enddefinitions $end


#0
b000 "
0#
0$
0%
b0000000000000000000000000000 &
b000 '
0(
0)
b0000 *
0+
b000000000000 ,
0-
0.
b0000 /
00
b10000 1
b10000 2
b00000000000000000 3
04
05
06
07
b00 8
b00 9
1:
b0000 ;
b00000000 <
0=
b0000 >
0?
b0000 @
0A
b000000000000 B
b00000000000000000000000100000000 C
b0000 D
0E
b00 F
0G
b000000 H
b00000000000000000000000000000000 I
0J
1K
b00000000000000000000000000000011 L
b00000000000000000000000000011001 M
b00000000000000000000000000001011 N
b00000000000000000000000000000100 O
b00 P
b10 Q
b01 R
#10000
b0000000000000000000000000001 &
15
17
#20000
05
07
1=
b01 F
#30000
b0000000000000000000000000010 &
15
17
b01 8
b11 9
b00000011 <
#40000
05
07
b000000000001 B
#50000
b0000000000000000000000000011 &
15
17
#60000
05
07
b000000000010 B
#70000
b0000000000000000000000000100 &
15
17
#80000
05
07
b000000000011 B
#90000
b0000000000000000000000000101 &
15
17
#100000
05
07
b0001 ;
b0001 >
b000000000100 B
#110000
b0000000000000000000000000110 &
15
17
b00 9
b00000000 <
#120000
10
05
07
b0000 ;
b0000 >
b000000000101 B
#130000
b0000000000000000000000000111 &
15
17
b11 9
b00000011 <
#140000
05
07
b0010 ;
b0010 >
b000000000110 B
b0011 D
1E
#150000
b0000000000000000000000001000 &
15
17
#160000
05
07
b0000 ;
b0000 >
1?
b1111 @
b000000000111 B
b1111 D
0E
#170000
b0000000000000000000000001001 &
15
17
#180000
b01111 1
b00000000000011110 3
05
07
b0011 ;
b0011 >
0?
b0000 @
b000000001000 B
1E
#190000
b0000000000000000000000001010 &
15
17
#200000
05
07
b0000 ;
b0000 >
1?
b1111 @
b000000001001 B
0E
#210000
b0000000000000000000000001011 &
15
17
#220000
b01110 1
b00000000111111110 3
05
07
b0100 ;
b0100 >
0?
b0000 @
b000000001010 B
1E
#230000
b0000000000000000000000001100 &
15
17
#240000
05
07
b0000 ;
b0000 >
1?
b1111 @
b000000001011 B
0E
#250000
b0000000000000000000000001101 &
15
17
#260000
b01101 1
b00001111111111110 3
05
07
b0101 ;
b0101 >
0?
b0000 @
b000000001100 B
1E
#270000
b0000000000000000000000001110 &
15
17
#280000
05
07
b0000 ;
b0000 >
1?
b1111 @
b000000001101 B
0E
#290000
b0000000000000000000000001111 &
15
17
#300000
b01100 1
b11111111111111110 3
05
07
b0110 ;
b0110 >
0?
b0000 @
b000000001110 B
1E
#310000
b0000000000000000000000010000 &
15
17
#320000
05
07
b0000 ;
b0000 >
1?
b1111 @
b000000001111 B
0E
#330000
b0000000000000000000000010001 &
15
17
#340000
b01011 1
14
05
07
b0111 ;
b0111 >
0?
b0000 @
b000000010000 B
1E
#350000
b0000000000000000000000010010 &
15
17
#360000
05
07
b0000 ;
b0000 >
1?
b1111 @
b000000010001 B
0E
#370000
b0000000000000000000000010011 &
15
17
#380000
b01010 1
05
07
b1000 ;
b1000 >
0?
b0000 @
b000000010010 B
1E
#390000
b0000000000000000000000010100 &
15
17
#400000
05
07
b0000 ;
b0000 >
1?
b1111 @
b000000010011 B
0E
#410000
b0000000000000000000000010101 &
15
17
#420000
b01001 1
05
07
b1001 ;
b1001 >
0?
b0000 @
b000000010100 B
1E
#430000
b0000000000000000000000010110 &
15
17
#440000
05
07
b0000 ;
b0000 >
1?
b1111 @
b000000010101 B
0E
#450000
b0000000000000000000000010111 &
15
17
#460000
b01000 1
05
07
b1010 ;
b1010 >
0?
b0000 @
b000000010110 B
1E
#470000
b0000000000000000000000011000 &
15
17
#480000
05
07
b0000 ;
b0000 >
1?
b1111 @
b000000010111 B
0E
#490000
b0000000000000000000000011001 &
15
17
#500000
b00111 1
05
07
b1011 ;
b1011 >
0?
b0000 @
b000000011000 B
1E
#510000
b0000000000000000000000011010 &
15
17
#520000
05
07
b0000 ;
b0000 >
1?
b1111 @
b000000011001 B
0E
#530000
b0000000000000000000000011011 &
15
17
#540000
b00110 1
05
07
b1100 ;
b1100 >
0?
b0000 @
b000000011010 B
1E
#550000
b0000000000000000000000011100 &
15
17
#560000
05
07
b0000 ;
b0000 >
1?
b1111 @
b000000011011 B
0E
#570000
b0000000000000000000000011101 &
15
17
#580000
b00101 1
05
07
b1101 ;
b1101 >
0?
b0000 @
b000000011100 B
1E
#590000
b0000000000000000000000011110 &
15
17
#600000
05
07
b0000 ;
b0000 >
1?
b1111 @
b000000011101 B
0E
#610000
b0000000000000000000000011111 &
15
17
#620000
b00100 1
05
07
b1110 ;
b1110 >
0?
b0000 @
b000000011110 B
1E
#630000
b0000000000000000000000100000 &
15
17
#640000
05
07
b0000 ;
b0000 >
1?
b1111 @
b000000011111 B
0E
#650000
b0000000000000000000000100001 &
15
17
#660000
b00011 1
05
07
b1111 ;
b1111 >
0?
b0000 @
b000000100000 B
1E
#670000
b0000000000000000000000100010 &
15
17
#680000
05
07
b0001 ;
b0001 >
1?
b1111 @
b000000100001 B
0E
#690000
b0000000000000000000000100011 &
15
17
#700000
b00010 1
05
07
b0000 ;
b0000 >
0?
b0000 @
b000000100010 B
1E
#710000
b0000000000000000000000100100 &
15
17
#720000
05
07
b0001 ;
b0001 >
1?
b1111 @
b000000100011 B
0E
#730000
b0000000000000000000000100101 &
15
17
#740000
b00001 1
05
07
0?
b0000 @
b000000100100 B
1E
#750000
b0000000000000000000000100110 &
15
17
#760000
05
07
1?
b1111 @
b000000100101 B
0E
#770000
b0000000000000000000000100111 &
15
17
#780000
b00000 1
05
07
b0010 ;
b0010 >
0?
b0000 @
b000000100110 B
1E
#790000
b0000000000000000000000101000 &
15
17
#800000
05
07
b0001 ;
b0001 >
1?
b1111 @
b000000100111 B
0E
#810000
b0000000000000000000000101001 &
15
17
#820000
b01111 2
b11111111111111101 3
05
07
b0011 ;
b0011 >
0?
b0000 @
b000000101000 B
1E
#830000
b0000000000000000000000101010 &
15
17
#840000
05
07
b0001 ;
b0001 >
1?
b1111 @
b000000101001 B
0E
#850000
b0000000000000000000000101011 &
15
17
